metocean_ml/__init__.py
metocean_ml/ml.py
metocean_ml-0.0.1.dist-info/LICENSE
metocean_ml-0.0.1.dist-info/METADATA
metocean_ml-0.0.1.dist-info/WHEEL
metocean_ml-0.0.1.dist-info/entry_points.txt
metocean_ml-0.0.1.dist-info/RECORD
